lsoft_types/BusinessRelation.py
lsoft_types/TAddress.py
lsoft_types/TContact.py
lsoft_types/TGpsrData.py
lsoft_types/TLink.py
lsoft_types/TLocation.py
lsoft_types-0.1.0.dist-info/METADATA
lsoft_types-0.1.0.dist-info/WHEEL
lsoft_types-0.1.0.dist-info/entry_points.txt
lsoft_types-0.1.0.dist-info/RECORD
