Metadata-Version: 2.1
Name: lsoft-types
Version: 0.1.0
Summary: description goes here
Author: IT
Author-email: it@electronic-shop.lu
Requires-Python: >=3.12,<4.0
Classifier: Programming Language :: Python :: 3
Requires-Dist: lsmeta-pydantic (>=1.0.1,<2.0.0)
